flash_pref/__init__.py
flash_pref/flash_dpo_trainer.py
flash_pref/flash_reward_trainer.py
flash_pref/shared_prefix.py
flash_pref-0.1.1.dist-info/licenses/LICENSE
flash_pref-0.1.1.dist-info/METADATA
flash_pref-0.1.1.dist-info/WHEEL
flash_pref-0.1.1.dist-info/top_level.txt
flash_pref-0.1.1.dist-info/RECORD
