Metadata-Version: 2.4
Name: flash-pref
Version: 0.1.1
Summary: Accelerate LLM preference finetuning with a single line of code
Author-email: Jiahao Li <liplus17@163.com>
Maintainer-email: Jiahao Li <liplus17@163.com>
License: MIT License
Project-URL: Homepage, https://github.com/li-plus/flash-preference
Project-URL: Repository, https://github.com/li-plus/flash-preference.git
Keywords: Prefix Sharing,Direct Preference Optimization,Reward Model,Preference Tuning
Classifier: Development Status :: 3 - Alpha
Classifier: Intended Audience :: Science/Research
Classifier: Topic :: Scientific/Engineering :: Artificial Intelligence
Classifier: License :: OSI Approved :: MIT License
Classifier: Programming Language :: Python :: 3.8
Classifier: Programming Language :: Python :: 3.9
Classifier: Programming Language :: Python :: 3.10
Classifier: Programming Language :: Python :: 3.11
Classifier: Programming Language :: Python :: 3.12
Requires-Python: >=3.7
License-File: LICENSE
Requires-Dist: transformers<4.52.0,>=4.49.0
Dynamic: license-file
